chemcalc_lib/__init__.py
chemcalc_lib/core.py
chemcalc_lib-0.1.3.dist-info/licenses/LICENSE
examples/__init__.py
examples/basic_examples.py
examples/paper_examples.py
examples/recursive_example.py
tests/__init__.py
tests/test_basic.py
tests/test_recursive.py
chemcalc_lib-0.1.3.dist-info/METADATA
chemcalc_lib-0.1.3.dist-info/WHEEL
chemcalc_lib-0.1.3.dist-info/top_level.txt
chemcalc_lib-0.1.3.dist-info/RECORD
