Metadata-Version: 2.4
Name: chemcalc_lib
Version: 0.1.3
Summary: A library for chemical mixture calculations and composition conversions
Home-page: https://github.com/TheophileGaudin/chemcalc-lib
Author: Théophile Gaudin
Author-email: Théophile Gaudin <gaudin.theophile@gmail.com>
License: MIT
Project-URL: Homepage, https://github.com/TheophileGaudin/chemcalc-lib
Project-URL: Repository, https://github.com/TheophileGaudin/chemcalc-lib.git
Project-URL: Issues, https://github.com/TheophileGaudin/chemcalc-lib/issues
Project-URL: Documentation, https://github.com/TheophileGaudin/chemcalc-lib/blob/main/README.md
Keywords: chemistry,mixture,mole fraction,composition,chemical calculations
Classifier: Development Status :: 4 - Beta
Classifier: Intended Audience :: Science/Research
Classifier: License :: OSI Approved :: MIT License
Classifier: Operating System :: OS Independent
Classifier: Programming Language :: Python :: 3
Classifier: Programming Language :: Python :: 3.8
Classifier: Programming Language :: Python :: 3.9
Classifier: Programming Language :: Python :: 3.10
Classifier: Programming Language :: Python :: 3.11
Classifier: Programming Language :: Python :: 3.12
Classifier: Topic :: Scientific/Engineering :: Chemistry
Classifier: Topic :: Scientific/Engineering :: Mathematics
Requires-Python: >=3.8
License-File: LICENSE
Requires-Dist: numpy>=1.19.0
Dynamic: author
Dynamic: home-page
Dynamic: license-file
Dynamic: requires-python
